resizePixel/__init__.py
resizePixel/resizePixel.py
resizePixel/version.py
tests/__init__.py
tests/unit/__init__.py
tests/unit/test_resizePixel.py
tests/unit/test_version.py
resizePixel-1.0.0.dist-info/LICENSE
resizePixel-1.0.0.dist-info/METADATA
resizePixel-1.0.0.dist-info/WHEEL
resizePixel-1.0.0.dist-info/top_level.txt
resizePixel-1.0.0.dist-info/RECORD
