Metadata-Version: 2.1
Name: resizePixel
Version: 1.0.0
Summary: Python Resize Pixel
Home-page: UNKNOWN
Author: mkshgh
Author-email: <mukesh.ghimire@outlook.com>
License: UNKNOWN
Keywords: python,image,image quality,reduce,increase,frustrated
Platform: UNKNOWN
Classifier: Programming Language :: Python :: 3
Classifier: License :: OSI Approved :: MIT License
Classifier: Operating System :: OS Independent
Requires-Python: >3.7
Requires-Dist: pytest
Requires-Dist: pytest-cov
